[{"\u9884\u8ba1\u884c\u7a0b\u65f6\u95f4": "8 h 10 min", "\u884c\u7a0b\u8d77\u6b62\u65f6\u95f4": "10:58 AM\u20147:08 PM", "\u4e3b\u8981\u7ecf\u8fc7\u7ebf\u8def": "Midosuji Line Tokaido-Sanyo Shinkansen Tohoku Shinkansen Hakodate Line", "\u51fa\u53d1\u65f6\u95f4\u548c\u7ad9\u70b9": "11:04 AM from Yodoyabashi Station", "\u9884\u8ba1\u82b1\u8d39": "\u00a532,540", "\u6b65\u884c\u65f6\u5e38": "20", "\u8be6\u60c5": "10:58 AM\nOsaka\nOsaka Prefecture, Japan\nWalk\nAbout 6 min , 450 m\n11:04 AM\nYodoyabashi Station\nMidosuji Line\u5404\u505cSenrichuo\n9 min (4 stops)\n11:13 AM\nShin-Osaka Station\nWalk\nAbout 4 min\n11:30 AM\nShin-Osaka Station\nTokaido-Sanyo ShinkansenNozomi 336\u306e\u305e\u307fTokyo\n2 h 33 min (5 stops)\n2:03 PM\nTokyo Station\nWalk\nAbout 1 min\n2:20 PM\nTokyo Station\n6:32 PM\nTohoku ShinkansenHayabusa 23\u306f\u3084\u3076\u3055Shin-Hakodate-Hokuto\n3 h 9 min (6 stops)\nContinue on the same vehicle\nTohoku ShinkansenHayabusa 23Shin-Hakodate-Hokuto\n1 h 1 min (non-stop)\n6:44 PM\nShin-Hakodate-Hokuto Station\nHakodate LineHakodate-Liner\u5feb\u901fHakodate\n15 min (2 stops)\n6:59 PM\nHakodate Station\nWalk\nAbout 9 min , 750 m\n7:08 PM\nHakodate\nHokkaido, Japan"}]