[{"\u9884\u8ba1\u884c\u7a0b\u65f6\u95f4": "1 h 45 min", "\u884c\u7a0b\u8d77\u6b62\u65f6\u95f4": "10:48 AM\u201412:33 PM", "\u4e3b\u8981\u7ecf\u8fc7\u7ebf\u8def": "8 Tokaido-Sanyo Shinkansen Yamaguchi Line", "\u51fa\u53d1\u65f6\u95f4\u548c\u7ad9\u70b9": "10:51 AM from Tenjin 1 chome(bus)", "\u9884\u8ba1\u82b1\u8d39": "\u00a56,130", "\u6b65\u884c\u65f6\u5e38": "25", "\u8be6\u60c5": "10:48 AM\nFukuoka\nFukuoka Prefecture, Japan\nWalk\nAbout 3 min , 230 m\n10:51 AM\nTenjin 1 chome(bus)\n8\u666eHakata Station []\n11 min (6 stops)\n11:02 AM\nHAKATA BUS TERMINAL\nWalk\nAbout 4 min\n11:10 AM\nHakata Station\nTokaido-Sanyo ShinkansenNozomi 24\u306e\u305e\u307fTokyo\n35 min (2 stops)\n11:45 AM\nShin-Yamaguchi Station\nWalk\nAbout 1 min\n11:53 AM\nShin-Yamaguchi Station\nYamaguchi Line\u5404\u505cYamaguchi\n23 min (7 stops) \u00b7 Platform 1\n12:16 PM\nYamaguchi Station\nWalk\nAbout 17 min , 1.4 km\n12:33 PM\nYamaguchi\nYamaguchi Prefecture, Japan"}]