[{"\u9884\u8ba1\u884c\u7a0b\u65f6\u95f4": "7 h 10 min", "\u884c\u7a0b\u8d77\u6b62\u65f6\u95f4": "10:46 AM\u20145:56 PM", "\u4e3b\u8981\u7ecf\u8fc7\u7ebf\u8def": "Shinano Kansai Line Kisei Line", "\u51fa\u53d1\u65f6\u95f4\u548c\u7ad9\u70b9": "11:00 AM from Nagano Station", "\u9884\u8ba1\u82b1\u8d39": "\u00a59,500", "\u6b65\u884c\u65f6\u5e38": "18", "\u8be6\u60c5": "10:46 AM\nNagano\nNagano Prefecture, Japan\nWalk\nAbout 14 min , 1.1 km\n11:00 AM\nNagano Station\n2:01 PM\nShinanoShinano 10Limited ExpressNagoya\n3 h 1 min (8 stops)\n2:06 PM\nNagoya Station\n3:08 PM\nKansai Line\u5feb\u901fKameyama\n1 h 2 min (8 stops)\n3:14 PM\nKameyama Station\nKisei Line\u5404\u505cShingu\n2 h 38 min (20 stops)\n5:52 PM\nKii-Nagashima Station\nWalk\nAbout 4 min , 350 m\n5:56 PM\nKihoku\nKitamuro District, Mie Prefecture, Japan"}]