[{"\u9884\u8ba1\u884c\u7a0b\u65f6\u95f4": "7 h 31 min", "\u884c\u7a0b\u8d77\u6b62\u65f6\u95f4": "10:08 AM\u20145:39 PM", "\u4e3b\u8981\u7ecf\u8fc7\u7ebf\u8def": "\uff24\uff11\uff13\uff10\u30fb\uff33\uff11\uff13\uff10 Akita Shinkansen Tokaido-Sanyo Shinkansen \u795e\u6238\uff5e\u5fb3\u5cf6\uff1a\u963f\u6ce2\uff25\uff38\uff30", "\u51fa\u53d1\u65f6\u95f4\u548c\u7ad9\u70b9": "10:10 AM from \u770c\u5e81\u5e02\u5f79\u6240\u524d\uff3b\u4ed9\u53f0\u5e02\uff3d\uff08\u30d0\u30b9\uff09", "\u9884\u8ba1\u82b1\u8d39": "\u00a526,060", "\u6b65\u884c\u65f6\u5e38": "16", "\u8be6\u60c5": "10:08 AM\nSendai\nMiyagi Prefecture, Japan\nWalk\nAbout 2 min , 130 m\n10:10 AM\n\u770c\u5e81\u5e02\u5f79\u6240\u524d\uff3b\u4ed9\u53f0\u5e02\uff3d\uff08\u30d0\u30b9\uff09\n\uff24\uff11\uff13\uff10\u30fb\uff33\uff11\uff13\uff10\u4ed9\u53f0\u99c5\u524d\u884c\n13 min (4 stops)\n10:23 AM\n\u4ed9\u53f0\u99c5\u524d\uff08\u30d0\u30b9\uff09\nWalk\nAbout 2 min\n10:30 AM\nSendai Station\nAkita ShinkansenKomachi 12\u3053\u307e\u3061Tokyo\n1 h 34 min (3 stops)\n12:04 PM\nTokyo Station\nWalk\nAbout 1 min\n12:30 PM\nTokyo Station\nTokaido-Sanyo ShinkansenNozomi 33\u306e\u305e\u307fHakata\n2 h 47 min (6 stops)\n3:17 PM\nShin-K\u014dbe Station\nWalk\nAbout 5 min\n3:25 PM\n\u65b0\u795e\u6238\u99c5\uff08\u30d0\u30b9\uff09\n\u795e\u6238\uff5e\u5fb3\u5cf6\uff1a\u963f\u6ce2\uff25\uff38\uff30\u5fb3\u5cf6\u99c5\u524d\u884c\n2 h 8 min (7 stops)\n5:33 PM\nTokushima Bus Terminal\nWalk\nAbout 6 min , 550 m\n5:39 PM\nTokushima\nTokushima Prefecture, Japan"}]