[{"\u9884\u8ba1\u884c\u7a0b\u65f6\u95f4": "8 h 30 min", "\u884c\u7a0b\u8d77\u6b62\u65f6\u95f4": "11:50 AM\u20148:20 PM", "\u4e3b\u8981\u7ecf\u8fc7\u7ebf\u8def": "Hakodate Line Tohoku Shinkansen Tokaido-Sanyo Shinkansen Tokaido-Sanyo Line \u9577\u5ca1\u4eac\u7dda\uff18\uff10\u7cfb\u7d71", "\u51fa\u53d1\u65f6\u95f4\u548c\u7ad9\u70b9": "12:00 PM from Hakodate Station", "\u9884\u8ba1\u82b1\u8d39": "\u00a532,460", "\u6b65\u884c\u65f6\u5e38": "17", "\u8be6\u60c5": "11:50 AM\nHakodate\nHokkaido, Japan\nWalk\nAbout 10 min , 750 m\n12:00 PM\nHakodate Station\n12:22 PM\nHakodate LineHakodate-Liner\u5404\u505cShin-Hakodate-Hokuto\n22 min (5 stops)\n12:44 PM\nShin-Hakodate-Hokuto Station\nTohoku ShinkansenHayabusa 22\u306f\u3084\u3076\u3055Tokyo\n1 h 6 min (3 stops)\nContinue on the same vehicle\nTohoku ShinkansenHayabusa 22Tokyo\n3 h 12 min (6 stops)\n5:04 PM\nTokyo Station\nWalk\nAbout 1 min\n5:20 PM\nTokyo Station\nTokaido-Sanyo ShinkansenNozomi 245\u306e\u305e\u307fShin-Osaka\n2 h 18 min (4 stops)\n7:38 PM\nKyoto Station\nWalk\nAbout 3 min\n7:52 PM\nKyoto Station\nTokaido-Sanyo Line\u5404\u505cAboshi\n15 min (5 stops)\n8:07 PM\nYamazaki Station\nWalk\nAbout 1 min\n8:13 PM\n\uff2a\uff32\u5c71\u5d0e\uff08\u30d0\u30b9\uff09\n\u9577\u5ca1\u4eac\u7dda\uff18\uff10\u7cfb\u7d71\u962a\u6025\u6771\u5411\u65e5\u884c\n5 min (4 stops)\n8:18 PM\n\u5927\u5c71\u5d0e\u753a\u5f79\u5834\u524d\uff08\u30d0\u30b9\uff09\nWalk\nAbout 2 min , 180 m\n8:20 PM\nOyamazaki\nOtokuni District, Kyoto Prefecture, Japan"}]