[{"\u9884\u8ba1\u884c\u7a0b\u65f6\u95f4": "5 h 27 min", "\u884c\u7a0b\u8d77\u6b62\u65f6\u95f4": "10:01 AM\u20143:28 PM", "\u4e3b\u8981\u7ecf\u8fc7\u7ebf\u8def": "Chibatoshi-Monorail Sobu Line(Rapid) Tokaido-Sanyo Shinkansen Seto-Ohashi Line", "\u51fa\u53d1\u65f6\u95f4\u548c\u7ad9\u70b9": "10:04 AM from Shiyakusho-Mae Station", "\u9884\u8ba1\u82b1\u8d39": "\u00a518,440", "\u6b65\u884c\u65f6\u5e38": "13", "\u8be6\u60c5": "10:01 AM\nChiba\nChiba Prefecture, Japan\nWalk\nAbout 3 min , 160 m\n10:04 AM\nShiyakusho-Mae Station\nChibatoshi-Monorail\u5404\u505cChishirodai\n2 min (non-stop)\n10:06 AM\nChiba Station\nWalk\nAbout 2 min\n10:11 AM\nChiba Station\n11:01 AM\nSobu Line(Rapid)\u5feb\u901fZushi\n40 min (9 stops)\nContinue on the same vehicle\nYokosuka LineZushi\n9 min (2 stops)\n11:17 AM\nShinagawa Station\nTokaido-Sanyo ShinkansenNozomi 27\u306e\u305e\u307fHakata\n3 h 10 min (6 stops)\n2:27 PM\nOkayama Station\nWalk\nAbout 1 min\n2:42 PM\nOkayama Station\nSeto-Ohashi LineMarine Liner 39\u5feb\u901fTakamatsu\n39 min (4 stops)\n3:21 PM\nSakaide Station\nWalk\nAbout 7 min , 650 m\n3:28 PM\nSakaide\nKagawa Prefecture, Japan"}]