[{"\u9884\u8ba1\u884c\u7a0b\u65f6\u95f4": "2 h 24 min", "\u884c\u7a0b\u8d77\u6b62\u65f6\u95f4": "11:16 AM\u20141:40 PM", "\u4e3b\u8981\u7ecf\u8fc7\u7ebf\u8def": "\u672d\u5e4c\uff5e\u6817\u5c71 Muroran Line", "\u51fa\u53d1\u65f6\u95f4\u548c\u7ad9\u70b9": "11:20 AM from Chuo Bus Sapporo Terminal", "\u9884\u8ba1\u82b1\u8d39": "\u00a51,340", "\u6b65\u884c\u65f6\u5e38": "25", "\u8be6\u60c5": "11:16 AM\nSapporo\nHokkaido, Japan\nWalk\nAbout 4 min , 270 m\n11:20 AM\nChuo Bus Sapporo Terminal\n\u672d\u5e4c\uff5e\u6817\u5c71\u6817\u5c71\u99c5\u884c\n1 h 10 min (6 stops)\n12:30 PM\n\u6817\u5c71\u99c5\uff08\u30d0\u30b9\uff09\nWalk\nAbout 1 min\n1:15 PM\nKuriyama Station\nMuroran Line\u5404\u505cTomakomai\n5 min (non-stop)\n1:20 PM\nYuni Station\nWalk\nAbout 20 min , 1.7 km\n1:40 PM\nYuni\nYubari District, Hokkaido, Japan"}]