[{"\u9884\u8ba1\u884c\u7a0b\u65f6\u95f4": "10 h 53 min", "\u884c\u7a0b\u8d77\u6b62\u65f6\u95f4": "11:02 AM\u20149:55 PM", "\u4e3b\u8981\u7ecf\u8fc7\u7ebf\u8def": "Lilac-Kamui Hokuto Tohoku Shinkansen \u6771\u4eac\uff5e\u6728\u66f4\u6d25", "\u51fa\u53d1\u65f6\u95f4\u548c\u7ad9\u70b9": "11:02 AM from Takikawa Station", "\u9884\u8ba1\u82b1\u8d39": "\u00a529,950", "\u6b65\u884c\u65f6\u5e38": "4", "\u8be6\u60c5": "11:02 AM\nTakikawa Station\nJapan\n11:02 AM\nTakikawa Station\n11:55 AM\nLilac-KamuiLilac 18Limited ExpressSapporo\n53 min (4 stops)\n12:15 PM\nSapporo Station\n3:51 PM\nHokutoHokuto 12Limited ExpressHakodate\n3 h 36 min (12 stops)\n4:17 PM\nShin-Hakodate-Hokuto Station\nTohoku ShinkansenHayabusa 30\u306f\u3084\u3076\u3055Tokyo\n1 h 3 min (2 stops)\nContinue on the same vehicle\nTohoku ShinkansenHayabusa 30Tokyo\n3 h 10 min (5 stops)\n8:32 PM\nTokyo Station\nWalk\nAbout 3 min\n8:55 PM\nTokyoekiyaesuguchi\n\u6771\u4eac\uff5e\u6728\u66f4\u6d25\u541b\u6d25\u88fd\u9435\u6240\u884c\n59 min (2 stops)\n9:54 PM\nKisarazuekinishiguchi\nWalk\nAbout 1 min , 82 m\n9:55 PM\nKisarazu\nChiba Prefecture, Japan"}]